[{"brgy_code":"025010001","brgy_name":"Acacia","province_code":"0250","region_code":"02"},{"brgy_code":"025010002","brgy_name":"Amilong Labeng","province_code":"0250","region_code":"02"},{"brgy_code":"025010003","brgy_name":"Ansipsip","province_code":"0250","region_code":"02"},{"brgy_code":"025010004","brgy_name":"Baan","province_code":"0250","region_code":"02"},{"brgy_code":"025010005","brgy_name":"Babadi","province_code":"0250","region_code":"02"},{"brgy_code":"025010006","brgy_name":"Balangabang","province_code":"0250","region_code":"02"},{"brgy_code":"025010007","brgy_name":"Banao","province_code":"0250","region_code":"02"},{"brgy_code":"025010008","brgy_name":"Binalian","province_code":"0250","region_code":"02"},{"brgy_code":"025010009","brgy_name":"Besong","province_code":"0250","region_code":"02"},{"brgy_code":"025010010","brgy_name":"Cabalatan-Alang","province_code":"0250","region_code":"02"},{"brgy_code":"025010011","brgy_name":"Cabanglasan","province_code":"0250","region_code":"02"},{"brgy_code":"025010012","brgy_name":"Kayapa Proper East","province_code":"0250","region_code":"02"},{"brgy_code":"025010013","brgy_name":"Kayapa Proper West","province_code":"0250","region_code":"02"},{"brgy_code":"025010014","brgy_name":"Mapayao","province_code":"0250","region_code":"02"},{"brgy_code":"025010015","brgy_name":"Nansiakan","province_code":"0250","region_code":"02"},{"brgy_code":"025010016","brgy_name":"Pampang (Pob.)","province_code":"0250","region_code":"02"},{"brgy_code":"025010017","brgy_name":"Pangawan","province_code":"0250","region_code":"02"},{"brgy_code":"025010018","brgy_name":"Pinayag","province_code":"0250","region_code":"02"},{"brgy_code":"025010019","brgy_name":"Pingkian","province_code":"0250","region_code":"02"},{"brgy_code":"025010020","brgy_name":"San Fabian","province_code":"0250","region_code":"02"},{"brgy_code":"025010021","brgy_name":"Talecabcab","province_code":"0250","region_code":"02"},{"brgy_code":"025010022","brgy_name":"Tubongan","province_code":"0250","region_code":"02"},{"brgy_code":"025010023","brgy_name":"Alang-Salacsac","province_code":"0250","region_code":"02"},{"brgy_code":"025010024","brgy_name":"Balete","province_code":"0250","region_code":"02"},{"brgy_code":"025010025","brgy_name":"Buyasyas","province_code":"0250","region_code":"02"},{"brgy_code":"025010026","brgy_name":"Cabayo","province_code":"0250","region_code":"02"},{"brgy_code":"025010027","brgy_name":"Castillo Village","province_code":"0250","region_code":"02"},{"brgy_code":"025010028","brgy_name":"Latbang","province_code":"0250","region_code":"02"},{"brgy_code":"025010029","brgy_name":"Lawigan","province_code":"0250","region_code":"02"},{"brgy_code":"025010030","brgy_name":"Tidang Village","province_code":"0250","region_code":"02"}]