[{"brgy_code":"025006001","brgy_name":"Arwas","province_code":"0250","region_code":"02"},{"brgy_code":"025006002","brgy_name":"Balete","province_code":"0250","region_code":"02"},{"brgy_code":"025006003","brgy_name":"Bugnay","province_code":"0250","region_code":"02"},{"brgy_code":"025006004","brgy_name":"Decabacan","province_code":"0250","region_code":"02"},{"brgy_code":"025006005","brgy_name":"Duruarog","province_code":"0250","region_code":"02"},{"brgy_code":"025006006","brgy_name":"Escoting","province_code":"0250","region_code":"02"},{"brgy_code":"025006007","brgy_name":"Nagsabaran","province_code":"0250","region_code":"02"},{"brgy_code":"025006008","brgy_name":"Namamparan","province_code":"0250","region_code":"02"},{"brgy_code":"025006009","brgy_name":"Pinya","province_code":"0250","region_code":"02"},{"brgy_code":"025006010","brgy_name":"Poblacion","province_code":"0250","region_code":"02"},{"brgy_code":"025006011","brgy_name":"Ampakling","province_code":"0250","region_code":"02"},{"brgy_code":"025006012","brgy_name":"Butao","province_code":"0250","region_code":"02"},{"brgy_code":"025006013","brgy_name":"Langca","province_code":"0250","region_code":"02"},{"brgy_code":"025006014","brgy_name":"Lurad","province_code":"0250","region_code":"02"},{"brgy_code":"025006015","brgy_name":"Rosario","province_code":"0250","region_code":"02"},{"brgy_code":"025006016","brgy_name":"San Luis","province_code":"0250","region_code":"02"},{"brgy_code":"025006017","brgy_name":"San Pablo","province_code":"0250","region_code":"02"},{"brgy_code":"025006018","brgy_name":"Villa Aurora","province_code":"0250","region_code":"02"},{"brgy_code":"025006019","brgy_name":"Villa Florentino","province_code":"0250","region_code":"02"}]