[{"brgy_code":"041031001","brgy_name":"Altura Bata","province_code":"0410","region_code":"04"},{"brgy_code":"041031002","brgy_name":"Altura Matanda","province_code":"0410","region_code":"04"},{"brgy_code":"041031003","brgy_name":"Altura-South","province_code":"0410","region_code":"04"},{"brgy_code":"041031004","brgy_name":"Ambulong","province_code":"0410","region_code":"04"},{"brgy_code":"041031005","brgy_name":"Banadero","province_code":"0410","region_code":"04"},{"brgy_code":"041031006","brgy_name":"Bagbag","province_code":"0410","region_code":"04"},{"brgy_code":"041031007","brgy_name":"Bagumbayan","province_code":"0410","region_code":"04"},{"brgy_code":"041031008","brgy_name":"Balele","province_code":"0410","region_code":"04"},{"brgy_code":"041031010","brgy_name":"Banjo East","province_code":"0410","region_code":"04"},{"brgy_code":"041031011","brgy_name":"Banjo Laurel (Banjo West)","province_code":"0410","region_code":"04"},{"brgy_code":"041031013","brgy_name":"Bilog-bilog","province_code":"0410","region_code":"04"},{"brgy_code":"041031014","brgy_name":"Boot","province_code":"0410","region_code":"04"},{"brgy_code":"041031015","brgy_name":"Cale","province_code":"0410","region_code":"04"},{"brgy_code":"041031016","brgy_name":"Darasa","province_code":"0410","region_code":"04"},{"brgy_code":"041031017","brgy_name":"Pagaspas","province_code":"0410","region_code":"04"},{"brgy_code":"041031018","brgy_name":"Gonzales","province_code":"0410","region_code":"04"},{"brgy_code":"041031019","brgy_name":"Hidalgo","province_code":"0410","region_code":"04"},{"brgy_code":"041031020","brgy_name":"Janopol","province_code":"0410","region_code":"04"},{"brgy_code":"041031021","brgy_name":"Janopol Oriental","province_code":"0410","region_code":"04"},{"brgy_code":"041031022","brgy_name":"Laurel","province_code":"0410","region_code":"04"},{"brgy_code":"041031023","brgy_name":"Luyos","province_code":"0410","region_code":"04"},{"brgy_code":"041031024","brgy_name":"Mabini","province_code":"0410","region_code":"04"},{"brgy_code":"041031025","brgy_name":"Malaking Pulo","province_code":"0410","region_code":"04"},{"brgy_code":"041031026","brgy_name":"Maria Paz","province_code":"0410","region_code":"04"},{"brgy_code":"041031027","brgy_name":"Maugat","province_code":"0410","region_code":"04"},{"brgy_code":"041031028","brgy_name":"Montaña (Ik-ik)","province_code":"0410","region_code":"04"},{"brgy_code":"041031029","brgy_name":"Natatas","province_code":"0410","region_code":"04"},{"brgy_code":"041031030","brgy_name":"Pantay Matanda","province_code":"0410","region_code":"04"},{"brgy_code":"041031031","brgy_name":"Pantay Bata","province_code":"0410","region_code":"04"},{"brgy_code":"041031032","brgy_name":"Poblacion Barangay 1","province_code":"0410","region_code":"04"},{"brgy_code":"041031033","brgy_name":"Poblacion Barangay 2","province_code":"0410","region_code":"04"},{"brgy_code":"041031034","brgy_name":"Poblacion Barangay 3","province_code":"0410","region_code":"04"},{"brgy_code":"041031035","brgy_name":"Poblacion Barangay 4","province_code":"0410","region_code":"04"},{"brgy_code":"041031036","brgy_name":"Poblacion Barangay 5","province_code":"0410","region_code":"04"},{"brgy_code":"041031037","brgy_name":"Poblacion Barangay 6","province_code":"0410","region_code":"04"},{"brgy_code":"041031038","brgy_name":"Poblacion Barangay 7","province_code":"0410","region_code":"04"},{"brgy_code":"041031039","brgy_name":"Sala","province_code":"0410","region_code":"04"},{"brgy_code":"041031040","brgy_name":"Sambat","province_code":"0410","region_code":"04"},{"brgy_code":"041031041","brgy_name":"San Jose","province_code":"0410","region_code":"04"},{"brgy_code":"041031042","brgy_name":"Santol (Doña Jacoba Garcia)","province_code":"0410","region_code":"04"},{"brgy_code":"041031043","brgy_name":"Santor","province_code":"0410","region_code":"04"},{"brgy_code":"041031044","brgy_name":"Sulpoc","province_code":"0410","region_code":"04"},{"brgy_code":"041031045","brgy_name":"Suplang","province_code":"0410","region_code":"04"},{"brgy_code":"041031046","brgy_name":"Talaga","province_code":"0410","region_code":"04"},{"brgy_code":"041031047","brgy_name":"Tinurik","province_code":"0410","region_code":"04"},{"brgy_code":"041031048","brgy_name":"Trapiche","province_code":"0410","region_code":"04"},{"brgy_code":"041031049","brgy_name":"Ulango","province_code":"0410","region_code":"04"},{"brgy_code":"041031050","brgy_name":"Wawa","province_code":"0410","region_code":"04"}]