[{"brgy_code":"043424001","brgy_name":"Bagong Bayan II-A (Pob.)","province_code":"0434","region_code":"04"},{"brgy_code":"043424002","brgy_name":"Bagong Pook VI-C (Pob.)","province_code":"0434","region_code":"04"},{"brgy_code":"043424003","brgy_name":"Barangay I-A (Pob.)","province_code":"0434","region_code":"04"},{"brgy_code":"043424004","brgy_name":"Barangay I-B (Pob.)","province_code":"0434","region_code":"04"},{"brgy_code":"043424005","brgy_name":"Barangay II-A (Pob.)","province_code":"0434","region_code":"04"},{"brgy_code":"043424006","brgy_name":"Barangay II-B (Pob.)","province_code":"0434","region_code":"04"},{"brgy_code":"043424007","brgy_name":"Barangay II-C (Pob.)","province_code":"0434","region_code":"04"},{"brgy_code":"043424008","brgy_name":"Barangay II-D (Pob.)","province_code":"0434","region_code":"04"},{"brgy_code":"043424009","brgy_name":"Barangay II-E (Pob.)","province_code":"0434","region_code":"04"},{"brgy_code":"043424010","brgy_name":"Barangay II-F (Pob.)","province_code":"0434","region_code":"04"},{"brgy_code":"043424011","brgy_name":"Barangay III-A (Pob.)","province_code":"0434","region_code":"04"},{"brgy_code":"043424012","brgy_name":"Barangay III-B (Pob.)","province_code":"0434","region_code":"04"},{"brgy_code":"043424013","brgy_name":"Barangay III-C (Pob.)","province_code":"0434","region_code":"04"},{"brgy_code":"043424014","brgy_name":"Barangay III-D (Pob.)","province_code":"0434","region_code":"04"},{"brgy_code":"043424015","brgy_name":"Barangay III-E (Pob.)","province_code":"0434","region_code":"04"},{"brgy_code":"043424016","brgy_name":"Barangay III-F (Pob.)","province_code":"0434","region_code":"04"},{"brgy_code":"043424017","brgy_name":"Barangay IV-A (Pob.)","province_code":"0434","region_code":"04"},{"brgy_code":"043424018","brgy_name":"Barangay IV-B (Pob.)","province_code":"0434","region_code":"04"},{"brgy_code":"043424019","brgy_name":"Barangay IV-C (Pob.)","province_code":"0434","region_code":"04"},{"brgy_code":"043424020","brgy_name":"Barangay V-A (Pob.)","province_code":"0434","region_code":"04"},{"brgy_code":"043424021","brgy_name":"Barangay V-B (Pob.)","province_code":"0434","region_code":"04"},{"brgy_code":"043424022","brgy_name":"Barangay V-C (Pob.)","province_code":"0434","region_code":"04"},{"brgy_code":"043424023","brgy_name":"Barangay V-D (Pob.)","province_code":"0434","region_code":"04"},{"brgy_code":"043424024","brgy_name":"Barangay VI-A (Pob.)","province_code":"0434","region_code":"04"},{"brgy_code":"043424025","brgy_name":"Barangay VI-B (Pob.)","province_code":"0434","region_code":"04"},{"brgy_code":"043424027","brgy_name":"Barangay VI-D (Pob.)","province_code":"0434","region_code":"04"},{"brgy_code":"043424028","brgy_name":"Barangay VI-E (Pob.)","province_code":"0434","region_code":"04"},{"brgy_code":"043424029","brgy_name":"Barangay VII-A (Pob.)","province_code":"0434","region_code":"04"},{"brgy_code":"043424030","brgy_name":"Barangay VII-B (Pob.)","province_code":"0434","region_code":"04"},{"brgy_code":"043424031","brgy_name":"Barangay VII-C (Pob.)","province_code":"0434","region_code":"04"},{"brgy_code":"043424032","brgy_name":"Barangay VII-D (Pob.)","province_code":"0434","region_code":"04"},{"brgy_code":"043424033","brgy_name":"Barangay VII-E (Pob.)","province_code":"0434","region_code":"04"},{"brgy_code":"043424034","brgy_name":"Bautista","province_code":"0434","region_code":"04"},{"brgy_code":"043424035","brgy_name":"Concepcion","province_code":"0434","region_code":"04"},{"brgy_code":"043424036","brgy_name":"Del Remedio","province_code":"0434","region_code":"04"},{"brgy_code":"043424037","brgy_name":"Dolores","province_code":"0434","region_code":"04"},{"brgy_code":"043424040","brgy_name":"San Antonio 1","province_code":"0434","region_code":"04"},{"brgy_code":"043424041","brgy_name":"San Antonio 2","province_code":"0434","region_code":"04"},{"brgy_code":"043424042","brgy_name":"San Bartolome","province_code":"0434","region_code":"04"},{"brgy_code":"043424043","brgy_name":"San Buenaventura","province_code":"0434","region_code":"04"},{"brgy_code":"043424044","brgy_name":"San Crispin","province_code":"0434","region_code":"04"},{"brgy_code":"043424045","brgy_name":"San Cristobal","province_code":"0434","region_code":"04"},{"brgy_code":"043424046","brgy_name":"San Diego","province_code":"0434","region_code":"04"},{"brgy_code":"043424047","brgy_name":"San Francisco","province_code":"0434","region_code":"04"},{"brgy_code":"043424048","brgy_name":"San Gabriel","province_code":"0434","region_code":"04"},{"brgy_code":"043424049","brgy_name":"San Gregorio","province_code":"0434","region_code":"04"},{"brgy_code":"043424050","brgy_name":"San Ignacio","province_code":"0434","region_code":"04"},{"brgy_code":"043424051","brgy_name":"San Isidro","province_code":"0434","region_code":"04"},{"brgy_code":"043424052","brgy_name":"San Joaquin","province_code":"0434","region_code":"04"},{"brgy_code":"043424053","brgy_name":"San Jose","province_code":"0434","region_code":"04"},{"brgy_code":"043424054","brgy_name":"San Juan","province_code":"0434","region_code":"04"},{"brgy_code":"043424055","brgy_name":"San Lorenzo","province_code":"0434","region_code":"04"},{"brgy_code":"043424056","brgy_name":"San Lucas 1","province_code":"0434","region_code":"04"},{"brgy_code":"043424057","brgy_name":"San Lucas 2","province_code":"0434","region_code":"04"},{"brgy_code":"043424058","brgy_name":"San Marcos","province_code":"0434","region_code":"04"},{"brgy_code":"043424059","brgy_name":"San Mateo","province_code":"0434","region_code":"04"},{"brgy_code":"043424060","brgy_name":"San Miguel","province_code":"0434","region_code":"04"},{"brgy_code":"043424061","brgy_name":"San Nicolas","province_code":"0434","region_code":"04"},{"brgy_code":"043424062","brgy_name":"San Pedro","province_code":"0434","region_code":"04"},{"brgy_code":"043424063","brgy_name":"San Rafael","province_code":"0434","region_code":"04"},{"brgy_code":"043424064","brgy_name":"San Roque","province_code":"0434","region_code":"04"},{"brgy_code":"043424065","brgy_name":"San Vicente","province_code":"0434","region_code":"04"},{"brgy_code":"043424066","brgy_name":"Santa Ana","province_code":"0434","region_code":"04"},{"brgy_code":"043424067","brgy_name":"Santa Catalina","province_code":"0434","region_code":"04"},{"brgy_code":"043424068","brgy_name":"Santa Cruz","province_code":"0434","region_code":"04"},{"brgy_code":"043424069","brgy_name":"Santa Felomina","province_code":"0434","region_code":"04"},{"brgy_code":"043424070","brgy_name":"Santa Isabel","province_code":"0434","region_code":"04"},{"brgy_code":"043424071","brgy_name":"Santa Maria Magdalena","province_code":"0434","region_code":"04"},{"brgy_code":"043424072","brgy_name":"Santa Veronica","province_code":"0434","region_code":"04"},{"brgy_code":"043424073","brgy_name":"Santiago I","province_code":"0434","region_code":"04"},{"brgy_code":"043424074","brgy_name":"Santiago II","province_code":"0434","region_code":"04"},{"brgy_code":"043424075","brgy_name":"Santisimo Rosario","province_code":"0434","region_code":"04"},{"brgy_code":"043424076","brgy_name":"Santo Angel","province_code":"0434","region_code":"04"},{"brgy_code":"043424077","brgy_name":"Santo Cristo","province_code":"0434","region_code":"04"},{"brgy_code":"043424078","brgy_name":"Santo Niño","province_code":"0434","region_code":"04"},{"brgy_code":"043424079","brgy_name":"Soledad","province_code":"0434","region_code":"04"},{"brgy_code":"043424080","brgy_name":"Atisan","province_code":"0434","region_code":"04"},{"brgy_code":"043424081","brgy_name":"Santa Elena","province_code":"0434","region_code":"04"},{"brgy_code":"043424082","brgy_name":"Santa Maria","province_code":"0434","region_code":"04"},{"brgy_code":"043424083","brgy_name":"Santa Monica","province_code":"0434","region_code":"04"}]