[{"brgy_code":"051729001","brgy_name":"Ayugao","province_code":"0517","region_code":"05"},{"brgy_code":"051729002","brgy_name":"Bagong Sirang","province_code":"0517","region_code":"05"},{"brgy_code":"051729003","brgy_name":"Baliguian","province_code":"0517","region_code":"05"},{"brgy_code":"051729004","brgy_name":"Bantugan","province_code":"0517","region_code":"05"},{"brgy_code":"051729005","brgy_name":"Bicalen","province_code":"0517","region_code":"05"},{"brgy_code":"051729006","brgy_name":"Bitaogan","province_code":"0517","region_code":"05"},{"brgy_code":"051729007","brgy_name":"Buenavista","province_code":"0517","region_code":"05"},{"brgy_code":"051729008","brgy_name":"Bulalacao","province_code":"0517","region_code":"05"},{"brgy_code":"051729009","brgy_name":"Cagnipa","province_code":"0517","region_code":"05"},{"brgy_code":"051729010","brgy_name":"Lagha","province_code":"0517","region_code":"05"},{"brgy_code":"051729011","brgy_name":"Lidong","province_code":"0517","region_code":"05"},{"brgy_code":"051729012","brgy_name":"Liwacsa","province_code":"0517","region_code":"05"},{"brgy_code":"051729013","brgy_name":"Maangas","province_code":"0517","region_code":"05"},{"brgy_code":"051729014","brgy_name":"Pagsangahan","province_code":"0517","region_code":"05"},{"brgy_code":"051729016","brgy_name":"Patrocinio","province_code":"0517","region_code":"05"},{"brgy_code":"051729017","brgy_name":"Pili","province_code":"0517","region_code":"05"},{"brgy_code":"051729018","brgy_name":"Santa Maria (Pob.)","province_code":"0517","region_code":"05"},{"brgy_code":"051729019","brgy_name":"Tanawan","province_code":"0517","region_code":"05"}]