[{"brgy_code":"054112001","brgy_name":"Bacolod","province_code":"0541","region_code":"05"},{"brgy_code":"054112002","brgy_name":"Bangad","province_code":"0541","region_code":"05"},{"brgy_code":"054112003","brgy_name":"Bara","province_code":"0541","region_code":"05"},{"brgy_code":"054112004","brgy_name":"Bonbon","province_code":"0541","region_code":"05"},{"brgy_code":"054112005","brgy_name":"Calasuche","province_code":"0541","region_code":"05"},{"brgy_code":"054112006","brgy_name":"Calumpang (Taisan)","province_code":"0541","region_code":"05"},{"brgy_code":"054112007","brgy_name":"Capaculan","province_code":"0541","region_code":"05"},{"brgy_code":"054112008","brgy_name":"Cayabon","province_code":"0541","region_code":"05"},{"brgy_code":"054112009","brgy_name":"Guinluthangan","province_code":"0541","region_code":"05"},{"brgy_code":"054112010","brgy_name":"Jamorawon","province_code":"0541","region_code":"05"},{"brgy_code":"054112011","brgy_name":"Magsalangi","province_code":"0541","region_code":"05"},{"brgy_code":"054112012","brgy_name":"Matagbac","province_code":"0541","region_code":"05"},{"brgy_code":"054112013","brgy_name":"Matanglad","province_code":"0541","region_code":"05"},{"brgy_code":"054112014","brgy_name":"Matiporon","province_code":"0541","region_code":"05"},{"brgy_code":"054112015","brgy_name":"Moises R. Espinosa","province_code":"0541","region_code":"05"},{"brgy_code":"054112016","brgy_name":"Narangasan","province_code":"0541","region_code":"05"},{"brgy_code":"054112018","brgy_name":"Pamangpangon","province_code":"0541","region_code":"05"},{"brgy_code":"054112019","brgy_name":"Poblacion East","province_code":"0541","region_code":"05"},{"brgy_code":"054112020","brgy_name":"Poblacion West","province_code":"0541","region_code":"05"},{"brgy_code":"054112021","brgy_name":"Paraiso (Potot)","province_code":"0541","region_code":"05"},{"brgy_code":"054112022","brgy_name":"San Antonio","province_code":"0541","region_code":"05"},{"brgy_code":"054112023","brgy_name":"San Carlos","province_code":"0541","region_code":"05"},{"brgy_code":"054112024","brgy_name":"Sawmill","province_code":"0541","region_code":"05"},{"brgy_code":"054112025","brgy_name":"Tagbon","province_code":"0541","region_code":"05"},{"brgy_code":"054112026","brgy_name":"Tawad","province_code":"0541","region_code":"05"},{"brgy_code":"054112027","brgy_name":"Tigbao","province_code":"0541","region_code":"05"},{"brgy_code":"054112028","brgy_name":"Tinaclipan (Bato)","province_code":"0541","region_code":"05"}]