[{"brgy_code":"063032001","brgy_name":"Baclayan","province_code":"0630","region_code":"06"},{"brgy_code":"063032002","brgy_name":"Badiang","province_code":"0630","region_code":"06"},{"brgy_code":"063032003","brgy_name":"Balabag","province_code":"0630","region_code":"06"},{"brgy_code":"063032004","brgy_name":"Bilidan","province_code":"0630","region_code":"06"},{"brgy_code":"063032005","brgy_name":"Bita-og Gaja","province_code":"0630","region_code":"06"},{"brgy_code":"063032007","brgy_name":"Bololacao","province_code":"0630","region_code":"06"},{"brgy_code":"063032008","brgy_name":"Burot","province_code":"0630","region_code":"06"},{"brgy_code":"063032009","brgy_name":"Cabilauan","province_code":"0630","region_code":"06"},{"brgy_code":"063032010","brgy_name":"Cabugao","province_code":"0630","region_code":"06"},{"brgy_code":"063032012","brgy_name":"Cagban","province_code":"0630","region_code":"06"},{"brgy_code":"063032013","brgy_name":"Calumbuyan","province_code":"0630","region_code":"06"},{"brgy_code":"063032014","brgy_name":"Damires","province_code":"0630","region_code":"06"},{"brgy_code":"063032015","brgy_name":"Dawis","province_code":"0630","region_code":"06"},{"brgy_code":"063032016","brgy_name":"General Delgado","province_code":"0630","region_code":"06"},{"brgy_code":"063032017","brgy_name":"Guinobatan","province_code":"0630","region_code":"06"},{"brgy_code":"063032018","brgy_name":"Janipa-an Oeste","province_code":"0630","region_code":"06"},{"brgy_code":"063032019","brgy_name":"Jelicuon Este","province_code":"0630","region_code":"06"},{"brgy_code":"063032020","brgy_name":"Jelicuon Oeste","province_code":"0630","region_code":"06"},{"brgy_code":"063032021","brgy_name":"Pasil","province_code":"0630","region_code":"06"},{"brgy_code":"063032022","brgy_name":"Poblacion","province_code":"0630","region_code":"06"},{"brgy_code":"063032023","brgy_name":"Wari-wari","province_code":"0630","region_code":"06"}]