[{"brgy_code":"064519002","brgy_name":"Barangay 1 (Pob.)","province_code":"0645","region_code":"06"},{"brgy_code":"064519003","brgy_name":"Barangay 2 (Pob.)","province_code":"0645","region_code":"06"},{"brgy_code":"064519004","brgy_name":"Barangay 3 (Pob.)","province_code":"0645","region_code":"06"},{"brgy_code":"064519005","brgy_name":"Barangay 4 (Pob.)","province_code":"0645","region_code":"06"},{"brgy_code":"064519006","brgy_name":"Barangay 5 (Pob.)","province_code":"0645","region_code":"06"},{"brgy_code":"064519007","brgy_name":"Barangay 6 (Pob.)","province_code":"0645","region_code":"06"},{"brgy_code":"064519008","brgy_name":"Barangay 7 (Pob.)","province_code":"0645","region_code":"06"},{"brgy_code":"064519009","brgy_name":"Crossing Magallon","province_code":"0645","region_code":"06"},{"brgy_code":"064519010","brgy_name":"Guinpana-an","province_code":"0645","region_code":"06"},{"brgy_code":"064519011","brgy_name":"Inolingan","province_code":"0645","region_code":"06"},{"brgy_code":"064519012","brgy_name":"Macagahay","province_code":"0645","region_code":"06"},{"brgy_code":"064519013","brgy_name":"Magallon Cadre","province_code":"0645","region_code":"06"},{"brgy_code":"064519014","brgy_name":"Montilla","province_code":"0645","region_code":"06"},{"brgy_code":"064519015","brgy_name":"Odiong","province_code":"0645","region_code":"06"},{"brgy_code":"064519016","brgy_name":"Quintin Remo","province_code":"0645","region_code":"06"}]