[{"brgy_code":"074610001","brgy_name":"Bagacay","province_code":"0746","region_code":"07"},{"brgy_code":"074610002","brgy_name":"Bajumpandan","province_code":"0746","region_code":"07"},{"brgy_code":"074610003","brgy_name":"Balugo","province_code":"0746","region_code":"07"},{"brgy_code":"074610004","brgy_name":"Banilad","province_code":"0746","region_code":"07"},{"brgy_code":"074610005","brgy_name":"Bantayan","province_code":"0746","region_code":"07"},{"brgy_code":"074610006","brgy_name":"Batinguel","province_code":"0746","region_code":"07"},{"brgy_code":"074610007","brgy_name":"Bunao","province_code":"0746","region_code":"07"},{"brgy_code":"074610008","brgy_name":"Cadawinonan","province_code":"0746","region_code":"07"},{"brgy_code":"074610009","brgy_name":"Calindagan","province_code":"0746","region_code":"07"},{"brgy_code":"074610010","brgy_name":"Camanjac","province_code":"0746","region_code":"07"},{"brgy_code":"074610011","brgy_name":"Candau-ay","province_code":"0746","region_code":"07"},{"brgy_code":"074610012","brgy_name":"Cantil-e","province_code":"0746","region_code":"07"},{"brgy_code":"074610013","brgy_name":"Daro","province_code":"0746","region_code":"07"},{"brgy_code":"074610014","brgy_name":"Junob","province_code":"0746","region_code":"07"},{"brgy_code":"074610015","brgy_name":"Looc","province_code":"0746","region_code":"07"},{"brgy_code":"074610016","brgy_name":"Mangnao-Canal","province_code":"0746","region_code":"07"},{"brgy_code":"074610017","brgy_name":"Motong","province_code":"0746","region_code":"07"},{"brgy_code":"074610018","brgy_name":"Piapi","province_code":"0746","region_code":"07"},{"brgy_code":"074610019","brgy_name":"Poblacion No. 1 (Barangay 1)","province_code":"0746","region_code":"07"},{"brgy_code":"074610020","brgy_name":"Poblacion No. 2 (Barangay 2)","province_code":"0746","region_code":"07"},{"brgy_code":"074610021","brgy_name":"Poblacion No. 3 (Barangay 3)","province_code":"0746","region_code":"07"},{"brgy_code":"074610022","brgy_name":"Poblacion No. 4 (Barangay 4)","province_code":"0746","region_code":"07"},{"brgy_code":"074610023","brgy_name":"Poblacion No. 5 (Barangay 5)","province_code":"0746","region_code":"07"},{"brgy_code":"074610024","brgy_name":"Poblacion No. 6 (Barangay 6)","province_code":"0746","region_code":"07"},{"brgy_code":"074610025","brgy_name":"Poblacion No. 7 (Barangay 7)","province_code":"0746","region_code":"07"},{"brgy_code":"074610026","brgy_name":"Poblacion No. 8 (Barangay 8)","province_code":"0746","region_code":"07"},{"brgy_code":"074610027","brgy_name":"Pulantubig","province_code":"0746","region_code":"07"},{"brgy_code":"074610028","brgy_name":"Tabuctubig","province_code":"0746","region_code":"07"},{"brgy_code":"074610029","brgy_name":"Taclobo","province_code":"0746","region_code":"07"},{"brgy_code":"074610030","brgy_name":"Talay","province_code":"0746","region_code":"07"}]