[{"brgy_code":"083731001","brgy_name":"Campin","province_code":"0837","region_code":"08"},{"brgy_code":"083731002","brgy_name":"Cuatro De Agosto","province_code":"0837","region_code":"08"},{"brgy_code":"083731003","brgy_name":"Hilusig","province_code":"0837","region_code":"08"},{"brgy_code":"083731004","brgy_name":"Himamara","province_code":"0837","region_code":"08"},{"brgy_code":"083731005","brgy_name":"Hinaguimitan","province_code":"0837","region_code":"08"},{"brgy_code":"083731006","brgy_name":"Liberacion","province_code":"0837","region_code":"08"},{"brgy_code":"083731007","brgy_name":"Mabuhay","province_code":"0837","region_code":"08"},{"brgy_code":"083731008","brgy_name":"Mabunga","province_code":"0837","region_code":"08"},{"brgy_code":"083731009","brgy_name":"Magsuganao","province_code":"0837","region_code":"08"},{"brgy_code":"083731010","brgy_name":"Mahayag","province_code":"0837","region_code":"08"},{"brgy_code":"083731011","brgy_name":"Mahayahay","province_code":"0837","region_code":"08"},{"brgy_code":"083731012","brgy_name":"Malinao","province_code":"0837","region_code":"08"},{"brgy_code":"083731013","brgy_name":"Malipoon","province_code":"0837","region_code":"08"},{"brgy_code":"083731014","brgy_name":"Palañogan","province_code":"0837","region_code":"08"},{"brgy_code":"083731015","brgy_name":"Paril","province_code":"0837","region_code":"08"},{"brgy_code":"083731016","brgy_name":"Pinamonoan","province_code":"0837","region_code":"08"},{"brgy_code":"083731017","brgy_name":"Poblacion","province_code":"0837","region_code":"08"},{"brgy_code":"083731018","brgy_name":"Polahongon","province_code":"0837","region_code":"08"},{"brgy_code":"083731019","brgy_name":"San Isidro","province_code":"0837","region_code":"08"},{"brgy_code":"083731020","brgy_name":"San Juan","province_code":"0837","region_code":"08"},{"brgy_code":"083731021","brgy_name":"Santa Cruz","province_code":"0837","region_code":"08"},{"brgy_code":"083731022","brgy_name":"Tagaytay","province_code":"0837","region_code":"08"},{"brgy_code":"083731023","brgy_name":"Uguis","province_code":"0837","region_code":"08"},{"brgy_code":"083731024","brgy_name":"Union","province_code":"0837","region_code":"08"},{"brgy_code":"083731025","brgy_name":"Upper Mahaplag","province_code":"0837","region_code":"08"},{"brgy_code":"083731026","brgy_name":"Hiluctogan","province_code":"0837","region_code":"08"},{"brgy_code":"083731027","brgy_name":"Maligaya","province_code":"0837","region_code":"08"},{"brgy_code":"083731028","brgy_name":"Santo Niño","province_code":"0837","region_code":"08"}]