[{"brgy_code":"086001001","brgy_name":"Bacjao","province_code":"0860","region_code":"08"},{"brgy_code":"086001004","brgy_name":"Biasong I","province_code":"0860","region_code":"08"},{"brgy_code":"086001005","brgy_name":"Costa Rica","province_code":"0860","region_code":"08"},{"brgy_code":"086001007","brgy_name":"Guin-ansan","province_code":"0860","region_code":"08"},{"brgy_code":"086001008","brgy_name":"Kerikite","province_code":"0860","region_code":"08"},{"brgy_code":"086001011","brgy_name":"Lunang I (Look)","province_code":"0860","region_code":"08"},{"brgy_code":"086001012","brgy_name":"Lunang II","province_code":"0860","region_code":"08"},{"brgy_code":"086001013","brgy_name":"Malobago","province_code":"0860","region_code":"08"},{"brgy_code":"086001014","brgy_name":"Marasbaras","province_code":"0860","region_code":"08"},{"brgy_code":"086001017","brgy_name":"Panjobjoban I","province_code":"0860","region_code":"08"},{"brgy_code":"086001019","brgy_name":"Poblacion","province_code":"0860","region_code":"08"},{"brgy_code":"086001023","brgy_name":"Talahid","province_code":"0860","region_code":"08"},{"brgy_code":"086001024","brgy_name":"Tonga-tonga","province_code":"0860","region_code":"08"},{"brgy_code":"086001025","brgy_name":"Imelda (Badjang)","province_code":"0860","region_code":"08"},{"brgy_code":"086001026","brgy_name":"Biasong II","province_code":"0860","region_code":"08"},{"brgy_code":"086001027","brgy_name":"Costa Rica II","province_code":"0860","region_code":"08"},{"brgy_code":"086001028","brgy_name":"Mabuhay","province_code":"0860","region_code":"08"},{"brgy_code":"086001029","brgy_name":"Magsaysay","province_code":"0860","region_code":"08"},{"brgy_code":"086001030","brgy_name":"Panjobjoban II","province_code":"0860","region_code":"08"},{"brgy_code":"086001031","brgy_name":"Roño","province_code":"0860","region_code":"08"},{"brgy_code":"086001032","brgy_name":"San Isidro","province_code":"0860","region_code":"08"},{"brgy_code":"086001033","brgy_name":"San Jose","province_code":"0860","region_code":"08"},{"brgy_code":"086001034","brgy_name":"Veloso","province_code":"0860","region_code":"08"}]