[{"brgy_code":"086016001","brgy_name":"Agrupacion","province_code":"0860","region_code":"08"},{"brgy_code":"086016002","brgy_name":"Arapison","province_code":"0860","region_code":"08"},{"brgy_code":"086016003","brgy_name":"Avelino","province_code":"0860","region_code":"08"},{"brgy_code":"086016004","brgy_name":"Bahay","province_code":"0860","region_code":"08"},{"brgy_code":"086016005","brgy_name":"Balud","province_code":"0860","region_code":"08"},{"brgy_code":"086016006","brgy_name":"Bana-ao","province_code":"0860","region_code":"08"},{"brgy_code":"086016008","brgy_name":"Burabod","province_code":"0860","region_code":"08"},{"brgy_code":"086016009","brgy_name":"Cautod (Pob.)","province_code":"0860","region_code":"08"},{"brgy_code":"086016010","brgy_name":"Camperito","province_code":"0860","region_code":"08"},{"brgy_code":"086016011","brgy_name":"Campeig","province_code":"0860","region_code":"08"},{"brgy_code":"086016012","brgy_name":"Can-ipulan","province_code":"0860","region_code":"08"},{"brgy_code":"086016013","brgy_name":"Canmoros","province_code":"0860","region_code":"08"},{"brgy_code":"086016014","brgy_name":"Cinco","province_code":"0860","region_code":"08"},{"brgy_code":"086016015","brgy_name":"Curry","province_code":"0860","region_code":"08"},{"brgy_code":"086016016","brgy_name":"Gajo","province_code":"0860","region_code":"08"},{"brgy_code":"086016017","brgy_name":"Hindang","province_code":"0860","region_code":"08"},{"brgy_code":"086016018","brgy_name":"Ilo","province_code":"0860","region_code":"08"},{"brgy_code":"086016019","brgy_name":"Imelda","province_code":"0860","region_code":"08"},{"brgy_code":"086016020","brgy_name":"Inoraguiao","province_code":"0860","region_code":"08"},{"brgy_code":"086016021","brgy_name":"Jolacao","province_code":"0860","region_code":"08"},{"brgy_code":"086016022","brgy_name":"Lambao","province_code":"0860","region_code":"08"},{"brgy_code":"086016023","brgy_name":"Mabuhay","province_code":"0860","region_code":"08"},{"brgy_code":"086016024","brgy_name":"Mahayag","province_code":"0860","region_code":"08"},{"brgy_code":"086016025","brgy_name":"Monbon (Pob.)","province_code":"0860","region_code":"08"},{"brgy_code":"086016026","brgy_name":"Nabulo","province_code":"0860","region_code":"08"},{"brgy_code":"086016027","brgy_name":"Napuro","province_code":"0860","region_code":"08"},{"brgy_code":"086016028","brgy_name":"Palale","province_code":"0860","region_code":"08"},{"brgy_code":"086016029","brgy_name":"Panabatan","province_code":"0860","region_code":"08"},{"brgy_code":"086016030","brgy_name":"Panaruan","province_code":"0860","region_code":"08"},{"brgy_code":"086016031","brgy_name":"Roxas","province_code":"0860","region_code":"08"},{"brgy_code":"086016032","brgy_name":"Salvacion","province_code":"0860","region_code":"08"},{"brgy_code":"086016033","brgy_name":"Solsogon","province_code":"0860","region_code":"08"},{"brgy_code":"086016034","brgy_name":"Sundara","province_code":"0860","region_code":"08"},{"brgy_code":"086016035","brgy_name":"Cagsumji","province_code":"0860","region_code":"08"},{"brgy_code":"086016036","brgy_name":"Matayonas","province_code":"0860","region_code":"08"},{"brgy_code":"086016037","brgy_name":"Napuro II","province_code":"0860","region_code":"08"}]