[{"brgy_code":"097302001","brgy_name":"Acad","province_code":"0973","region_code":"09"},{"brgy_code":"097302002","brgy_name":"Alang-alang","province_code":"0973","region_code":"09"},{"brgy_code":"097302003","brgy_name":"Alegria","province_code":"0973","region_code":"09"},{"brgy_code":"097302004","brgy_name":"Anonang","province_code":"0973","region_code":"09"},{"brgy_code":"097302005","brgy_name":"Bagong Mandaue","province_code":"0973","region_code":"09"},{"brgy_code":"097302007","brgy_name":"Bagong Maslog","province_code":"0973","region_code":"09"},{"brgy_code":"097302008","brgy_name":"Bagong Oslob","province_code":"0973","region_code":"09"},{"brgy_code":"097302009","brgy_name":"Bagong Pitogo","province_code":"0973","region_code":"09"},{"brgy_code":"097302010","brgy_name":"Baki","province_code":"0973","region_code":"09"},{"brgy_code":"097302011","brgy_name":"Balas","province_code":"0973","region_code":"09"},{"brgy_code":"097302012","brgy_name":"Balide","province_code":"0973","region_code":"09"},{"brgy_code":"097302013","brgy_name":"Balintawak","province_code":"0973","region_code":"09"},{"brgy_code":"097302014","brgy_name":"Bayabas","province_code":"0973","region_code":"09"},{"brgy_code":"097302015","brgy_name":"Bemposa","province_code":"0973","region_code":"09"},{"brgy_code":"097302016","brgy_name":"Cabilinan","province_code":"0973","region_code":"09"},{"brgy_code":"097302017","brgy_name":"Campo Uno","province_code":"0973","region_code":"09"},{"brgy_code":"097302018","brgy_name":"Ceboneg","province_code":"0973","region_code":"09"},{"brgy_code":"097302019","brgy_name":"Commonwealth","province_code":"0973","region_code":"09"},{"brgy_code":"097302021","brgy_name":"Gubaan","province_code":"0973","region_code":"09"},{"brgy_code":"097302022","brgy_name":"Inasagan","province_code":"0973","region_code":"09"},{"brgy_code":"097302023","brgy_name":"Inroad","province_code":"0973","region_code":"09"},{"brgy_code":"097302024","brgy_name":"Kahayagan East (Katipunan)","province_code":"0973","region_code":"09"},{"brgy_code":"097302025","brgy_name":"Kahayagan West","province_code":"0973","region_code":"09"},{"brgy_code":"097302027","brgy_name":"Kauswagan","province_code":"0973","region_code":"09"},{"brgy_code":"097302028","brgy_name":"La Victoria","province_code":"0973","region_code":"09"},{"brgy_code":"097302029","brgy_name":"Lantungan","province_code":"0973","region_code":"09"},{"brgy_code":"097302031","brgy_name":"Libertad","province_code":"0973","region_code":"09"},{"brgy_code":"097302032","brgy_name":"Lintugop","province_code":"0973","region_code":"09"},{"brgy_code":"097302033","brgy_name":"Lubid","province_code":"0973","region_code":"09"},{"brgy_code":"097302034","brgy_name":"Maguikay","province_code":"0973","region_code":"09"},{"brgy_code":"097302035","brgy_name":"Mahayahay","province_code":"0973","region_code":"09"},{"brgy_code":"097302037","brgy_name":"Monte Alegre","province_code":"0973","region_code":"09"},{"brgy_code":"097302038","brgy_name":"Montela","province_code":"0973","region_code":"09"},{"brgy_code":"097302040","brgy_name":"Napo","province_code":"0973","region_code":"09"},{"brgy_code":"097302041","brgy_name":"Panaghiusa","province_code":"0973","region_code":"09"},{"brgy_code":"097302042","brgy_name":"Poblacion","province_code":"0973","region_code":"09"},{"brgy_code":"097302043","brgy_name":"Resthouse","province_code":"0973","region_code":"09"},{"brgy_code":"097302044","brgy_name":"Romarate","province_code":"0973","region_code":"09"},{"brgy_code":"097302045","brgy_name":"San Jose","province_code":"0973","region_code":"09"},{"brgy_code":"097302046","brgy_name":"San Juan","province_code":"0973","region_code":"09"},{"brgy_code":"097302047","brgy_name":"Sapa Loboc","province_code":"0973","region_code":"09"},{"brgy_code":"097302048","brgy_name":"Tagulalo","province_code":"0973","region_code":"09"},{"brgy_code":"097302050","brgy_name":"La Paz (Tinibtiban)","province_code":"0973","region_code":"09"},{"brgy_code":"097302052","brgy_name":"Waterfall","province_code":"0973","region_code":"09"}]