[{"brgy_code":"097333001","brgy_name":"Baking","province_code":"0973","region_code":"09"},{"brgy_code":"097333002","brgy_name":"Bagong Kahayag","province_code":"0973","region_code":"09"},{"brgy_code":"097333003","brgy_name":"Biswangan","province_code":"0973","region_code":"09"},{"brgy_code":"097333004","brgy_name":"Bululawan","province_code":"0973","region_code":"09"},{"brgy_code":"097333005","brgy_name":"Dagum","province_code":"0973","region_code":"09"},{"brgy_code":"097333006","brgy_name":"Gasa","province_code":"0973","region_code":"09"},{"brgy_code":"097333007","brgy_name":"Gatub","province_code":"0973","region_code":"09"},{"brgy_code":"097333008","brgy_name":"Poblacion (Lakewood)","province_code":"0973","region_code":"09"},{"brgy_code":"097333009","brgy_name":"Lukuan","province_code":"0973","region_code":"09"},{"brgy_code":"097333010","brgy_name":"Matalang","province_code":"0973","region_code":"09"},{"brgy_code":"097333011","brgy_name":"Sapang Pinoles","province_code":"0973","region_code":"09"},{"brgy_code":"097333012","brgy_name":"Sebuguey","province_code":"0973","region_code":"09"},{"brgy_code":"097333013","brgy_name":"Tiwales","province_code":"0973","region_code":"09"},{"brgy_code":"097333014","brgy_name":"Tubod","province_code":"0973","region_code":"09"}]