[{"brgy_code":"103508001","brgy_name":"Austin Heights","province_code":"1035","region_code":"10"},{"brgy_code":"103508002","brgy_name":"Baybay","province_code":"1035","region_code":"10"},{"brgy_code":"103508004","brgy_name":"Bubong","province_code":"1035","region_code":"10"},{"brgy_code":"103508005","brgy_name":"Caromatan","province_code":"1035","region_code":"10"},{"brgy_code":"103508006","brgy_name":"Inudaran","province_code":"1035","region_code":"10"},{"brgy_code":"103508007","brgy_name":"Kulasihan","province_code":"1035","region_code":"10"},{"brgy_code":"103508009","brgy_name":"Libertad","province_code":"1035","region_code":"10"},{"brgy_code":"103508010","brgy_name":"Lumbac","province_code":"1035","region_code":"10"},{"brgy_code":"103508011","brgy_name":"Manga","province_code":"1035","region_code":"10"},{"brgy_code":"103508012","brgy_name":"Matampay","province_code":"1035","region_code":"10"},{"brgy_code":"103508013","brgy_name":"Mukas","province_code":"1035","region_code":"10"},{"brgy_code":"103508014","brgy_name":"Muntay","province_code":"1035","region_code":"10"},{"brgy_code":"103508016","brgy_name":"Pagalungan","province_code":"1035","region_code":"10"},{"brgy_code":"103508017","brgy_name":"Palao","province_code":"1035","region_code":"10"},{"brgy_code":"103508018","brgy_name":"Pantaon","province_code":"1035","region_code":"10"},{"brgy_code":"103508019","brgy_name":"Pantar","province_code":"1035","region_code":"10"},{"brgy_code":"103508020","brgy_name":"Poblacion","province_code":"1035","region_code":"10"},{"brgy_code":"103508021","brgy_name":"Rebucon","province_code":"1035","region_code":"10"},{"brgy_code":"103508022","brgy_name":"Riverside","province_code":"1035","region_code":"10"},{"brgy_code":"103508023","brgy_name":"San Roque","province_code":"1035","region_code":"10"},{"brgy_code":"103508024","brgy_name":"Santo Niño","province_code":"1035","region_code":"10"},{"brgy_code":"103508025","brgy_name":"Simbuco","province_code":"1035","region_code":"10"},{"brgy_code":"103508026","brgy_name":"Small Banisilan","province_code":"1035","region_code":"10"},{"brgy_code":"103508027","brgy_name":"Sucodan","province_code":"1035","region_code":"10"},{"brgy_code":"103508028","brgy_name":"Tabigue","province_code":"1035","region_code":"10"},{"brgy_code":"103508029","brgy_name":"Titunod","province_code":"1035","region_code":"10"}]