[{"brgy_code":"112314001","brgy_name":"Cabidianan","province_code":"1123","region_code":"11"},{"brgy_code":"112314002","brgy_name":"Carcor","province_code":"1123","region_code":"11"},{"brgy_code":"112314003","brgy_name":"Del Monte","province_code":"1123","region_code":"11"},{"brgy_code":"112314004","brgy_name":"Del Pilar","province_code":"1123","region_code":"11"},{"brgy_code":"112314005","brgy_name":"El Salvador","province_code":"1123","region_code":"11"},{"brgy_code":"112314006","brgy_name":"Limba-an","province_code":"1123","region_code":"11"},{"brgy_code":"112314007","brgy_name":"Macgum","province_code":"1123","region_code":"11"},{"brgy_code":"112314008","brgy_name":"Mambing","province_code":"1123","region_code":"11"},{"brgy_code":"112314009","brgy_name":"Mesaoy","province_code":"1123","region_code":"11"},{"brgy_code":"112314010","brgy_name":"New Bohol","province_code":"1123","region_code":"11"},{"brgy_code":"112314011","brgy_name":"New Cortez","province_code":"1123","region_code":"11"},{"brgy_code":"112314012","brgy_name":"New Sambog","province_code":"1123","region_code":"11"},{"brgy_code":"112314013","brgy_name":"Patrocenio","province_code":"1123","region_code":"11"},{"brgy_code":"112314014","brgy_name":"Poblacion","province_code":"1123","region_code":"11"},{"brgy_code":"112314015","brgy_name":"San Roque","province_code":"1123","region_code":"11"},{"brgy_code":"112314016","brgy_name":"Santa Cruz","province_code":"1123","region_code":"11"},{"brgy_code":"112314017","brgy_name":"Santa Fe","province_code":"1123","region_code":"11"},{"brgy_code":"112314018","brgy_name":"Santo Niño","province_code":"1123","region_code":"11"},{"brgy_code":"112314019","brgy_name":"Suawon","province_code":"1123","region_code":"11"},{"brgy_code":"112314020","brgy_name":"San Jose","province_code":"1123","region_code":"11"}]