[{"brgy_code":"126508001","brgy_name":"Caridad (Cuyapon)","province_code":"1265","region_code":"12"},{"brgy_code":"126508002","brgy_name":"Didtaras","province_code":"1265","region_code":"12"},{"brgy_code":"126508004","brgy_name":"Gansing (Bilumen)","province_code":"1265","region_code":"12"},{"brgy_code":"126508005","brgy_name":"Kabulakan","province_code":"1265","region_code":"12"},{"brgy_code":"126508006","brgy_name":"Kapingkong","province_code":"1265","region_code":"12"},{"brgy_code":"126508007","brgy_name":"Katitisan","province_code":"1265","region_code":"12"},{"brgy_code":"126508008","brgy_name":"Lagao","province_code":"1265","region_code":"12"},{"brgy_code":"126508009","brgy_name":"Lilit","province_code":"1265","region_code":"12"},{"brgy_code":"126508010","brgy_name":"Madanding","province_code":"1265","region_code":"12"},{"brgy_code":"126508011","brgy_name":"Maligaya","province_code":"1265","region_code":"12"},{"brgy_code":"126508012","brgy_name":"Mamali","province_code":"1265","region_code":"12"},{"brgy_code":"126508013","brgy_name":"Matiompong","province_code":"1265","region_code":"12"},{"brgy_code":"126508014","brgy_name":"Midtapok","province_code":"1265","region_code":"12"},{"brgy_code":"126508015","brgy_name":"New Cebu","province_code":"1265","region_code":"12"},{"brgy_code":"126508016","brgy_name":"Palumbi","province_code":"1265","region_code":"12"},{"brgy_code":"126508017","brgy_name":"Pidtiguian","province_code":"1265","region_code":"12"},{"brgy_code":"126508018","brgy_name":"Pimbalayan","province_code":"1265","region_code":"12"},{"brgy_code":"126508019","brgy_name":"Pinguiaman","province_code":"1265","region_code":"12"},{"brgy_code":"126508020","brgy_name":"Poblacion (Lambayong)","province_code":"1265","region_code":"12"},{"brgy_code":"126508021","brgy_name":"Sadsalan","province_code":"1265","region_code":"12"},{"brgy_code":"126508022","brgy_name":"Seneben","province_code":"1265","region_code":"12"},{"brgy_code":"126508023","brgy_name":"Sigayan","province_code":"1265","region_code":"12"},{"brgy_code":"126508024","brgy_name":"Tambak","province_code":"1265","region_code":"12"},{"brgy_code":"126508025","brgy_name":"Tinumigues","province_code":"1265","region_code":"12"},{"brgy_code":"126508027","brgy_name":"Tumiao (Tinaga)","province_code":"1265","region_code":"12"},{"brgy_code":"126508028","brgy_name":"Udtong","province_code":"1265","region_code":"12"}]