[{"brgy_code":"140117001","brgy_name":"Dumayco","province_code":"1401","region_code":"14"},{"brgy_code":"140117002","brgy_name":"Lusuac","province_code":"1401","region_code":"14"},{"brgy_code":"140117003","brgy_name":"Namarabar","province_code":"1401","region_code":"14"},{"brgy_code":"140117004","brgy_name":"Patiao","province_code":"1401","region_code":"14"},{"brgy_code":"140117005","brgy_name":"Malamsit (Pau-Malamsit)","province_code":"1401","region_code":"14"},{"brgy_code":"140117006","brgy_name":"Poblacion","province_code":"1401","region_code":"14"},{"brgy_code":"140117007","brgy_name":"Riang (Tiang)","province_code":"1401","region_code":"14"},{"brgy_code":"140117008","brgy_name":"Santa Rosa","province_code":"1401","region_code":"14"},{"brgy_code":"140117009","brgy_name":"Tattawa","province_code":"1401","region_code":"14"}]