[{"brgy_code":"153810001","brgy_name":"Bagoenged","province_code":"1538","region_code":"15"},{"brgy_code":"153810004","brgy_name":"Buliok","province_code":"1538","region_code":"15"},{"brgy_code":"153810006","brgy_name":"Damalasak","province_code":"1538","region_code":"15"},{"brgy_code":"153810008","brgy_name":"Galakit","province_code":"1538","region_code":"15"},{"brgy_code":"153810009","brgy_name":"Inug-ug","province_code":"1538","region_code":"15"},{"brgy_code":"153810010","brgy_name":"Kalbugan","province_code":"1538","region_code":"15"},{"brgy_code":"153810013","brgy_name":"Kilangan","province_code":"1538","region_code":"15"},{"brgy_code":"153810014","brgy_name":"Kudal","province_code":"1538","region_code":"15"},{"brgy_code":"153810015","brgy_name":"Layog","province_code":"1538","region_code":"15"},{"brgy_code":"153810017","brgy_name":"Linandangan","province_code":"1538","region_code":"15"},{"brgy_code":"153810021","brgy_name":"Poblacion","province_code":"1538","region_code":"15"},{"brgy_code":"153810025","brgy_name":"Dalgan","province_code":"1538","region_code":"15"}]