[{"brgy_code":"153809001","brgy_name":"Bayanga Norte","province_code":"1538","region_code":"15"},{"brgy_code":"153809002","brgy_name":"Bayanga Sur","province_code":"1538","region_code":"15"},{"brgy_code":"153809003","brgy_name":"Bugasan Norte","province_code":"1538","region_code":"15"},{"brgy_code":"153809004","brgy_name":"Bugasan Sur (Pob.)","province_code":"1538","region_code":"15"},{"brgy_code":"153809005","brgy_name":"Kidama","province_code":"1538","region_code":"15"},{"brgy_code":"153809007","brgy_name":"Sapad","province_code":"1538","region_code":"15"},{"brgy_code":"153809008","brgy_name":"Langco","province_code":"1538","region_code":"15"},{"brgy_code":"153809009","brgy_name":"Langkong","province_code":"1538","region_code":"15"}]