[{"brgy_code":"153812001","brgy_name":"Alamada","province_code":"1538","region_code":"15"},{"brgy_code":"153812003","brgy_name":"Banatin","province_code":"1538","region_code":"15"},{"brgy_code":"153812004","brgy_name":"Banubo","province_code":"1538","region_code":"15"},{"brgy_code":"153812006","brgy_name":"Bulalo","province_code":"1538","region_code":"15"},{"brgy_code":"153812007","brgy_name":"Bulibod","province_code":"1538","region_code":"15"},{"brgy_code":"153812009","brgy_name":"Calsada","province_code":"1538","region_code":"15"},{"brgy_code":"153812010","brgy_name":"Crossing Simuay","province_code":"1538","region_code":"15"},{"brgy_code":"153812012","brgy_name":"Dalumangcob (Pob.)","province_code":"1538","region_code":"15"},{"brgy_code":"153812013","brgy_name":"Darapanan","province_code":"1538","region_code":"15"},{"brgy_code":"153812014","brgy_name":"Gang","province_code":"1538","region_code":"15"},{"brgy_code":"153812015","brgy_name":"Inawan","province_code":"1538","region_code":"15"},{"brgy_code":"153812016","brgy_name":"Kabuntalan","province_code":"1538","region_code":"15"},{"brgy_code":"153812017","brgy_name":"Kakar","province_code":"1538","region_code":"15"},{"brgy_code":"153812018","brgy_name":"Kapimpilan","province_code":"1538","region_code":"15"},{"brgy_code":"153812019","brgy_name":"Katidtuan","province_code":"1538","region_code":"15"},{"brgy_code":"153812020","brgy_name":"Katuli","province_code":"1538","region_code":"15"},{"brgy_code":"153812023","brgy_name":"Ladia","province_code":"1538","region_code":"15"},{"brgy_code":"153812024","brgy_name":"Limbo","province_code":"1538","region_code":"15"},{"brgy_code":"153812026","brgy_name":"Maidapa","province_code":"1538","region_code":"15"},{"brgy_code":"153812027","brgy_name":"Makaguiling","province_code":"1538","region_code":"15"},{"brgy_code":"153812028","brgy_name":"Katamlangan (Matampay)","province_code":"1538","region_code":"15"},{"brgy_code":"153812029","brgy_name":"Matengen","province_code":"1538","region_code":"15"},{"brgy_code":"153812030","brgy_name":"Mulaug","province_code":"1538","region_code":"15"},{"brgy_code":"153812031","brgy_name":"Nalinan","province_code":"1538","region_code":"15"},{"brgy_code":"153812033","brgy_name":"Nekitan","province_code":"1538","region_code":"15"},{"brgy_code":"153812034","brgy_name":"Olas","province_code":"1538","region_code":"15"},{"brgy_code":"153812035","brgy_name":"Panatan","province_code":"1538","region_code":"15"},{"brgy_code":"153812036","brgy_name":"Pigcalagan","province_code":"1538","region_code":"15"},{"brgy_code":"153812037","brgy_name":"Pigkelegan (Ibotegen)","province_code":"1538","region_code":"15"},{"brgy_code":"153812038","brgy_name":"Pinaring","province_code":"1538","region_code":"15"},{"brgy_code":"153812039","brgy_name":"Pingping","province_code":"1538","region_code":"15"},{"brgy_code":"153812040","brgy_name":"Raguisi","province_code":"1538","region_code":"15"},{"brgy_code":"153812041","brgy_name":"Rebuken","province_code":"1538","region_code":"15"},{"brgy_code":"153812042","brgy_name":"Salimbao","province_code":"1538","region_code":"15"},{"brgy_code":"153812043","brgy_name":"Sambolawan","province_code":"1538","region_code":"15"},{"brgy_code":"153812044","brgy_name":"Senditan","province_code":"1538","region_code":"15"},{"brgy_code":"153812051","brgy_name":"Ungap","province_code":"1538","region_code":"15"},{"brgy_code":"153812052","brgy_name":"Damaniog","province_code":"1538","region_code":"15"},{"brgy_code":"153812053","brgy_name":"Nara","province_code":"1538","region_code":"15"}]