[{"brgy_code":"156614003","brgy_name":"Banting","province_code":"1566","region_code":"15"},{"brgy_code":"156614010","brgy_name":"Hawan","province_code":"1566","region_code":"15"},{"brgy_code":"156614013","brgy_name":"Alu-Kabingaan","province_code":"1566","region_code":"15"},{"brgy_code":"156614014","brgy_name":"Kalang (Pob.)","province_code":"1566","region_code":"15"},{"brgy_code":"156614016","brgy_name":"Kamaunggi","province_code":"1566","region_code":"15"},{"brgy_code":"156614017","brgy_name":"Kanmangon","province_code":"1566","region_code":"15"},{"brgy_code":"156614018","brgy_name":"Kanaway","province_code":"1566","region_code":"15"},{"brgy_code":"156614019","brgy_name":"Kaumpang","province_code":"1566","region_code":"15"},{"brgy_code":"156614025","brgy_name":"Pagatpat","province_code":"1566","region_code":"15"},{"brgy_code":"156614027","brgy_name":"Pangdan","province_code":"1566","region_code":"15"},{"brgy_code":"156614028","brgy_name":"Puok","province_code":"1566","region_code":"15"},{"brgy_code":"156614030","brgy_name":"Sayli","province_code":"1566","region_code":"15"},{"brgy_code":"156614032","brgy_name":"Sumambat","province_code":"1566","region_code":"15"},{"brgy_code":"156614033","brgy_name":"Tangkapaan","province_code":"1566","region_code":"15"},{"brgy_code":"156614035","brgy_name":"Tulakan","province_code":"1566","region_code":"15"}]